streamshatter.py
streamshatter-1.1.11.dist-info/METADATA
streamshatter-1.1.11.dist-info/WHEEL
streamshatter-1.1.11.dist-info/entry_points.txt
streamshatter-1.1.11.dist-info/licenses/LICENSE
streamshatter-1.1.11.dist-info/RECORD
