Metadata-Version: 2.4
Name: streamshatter
Version: 1.1.11
Summary: Multiplexed chunked file downloader
Project-URL: Homepage, https://github.com/thomas-xin/streamshatter
Project-URL: Repository, https://github.com/thomas-xin/streamshatter
Project-URL: Issues, https://github.com/thomas-xin/streamshatter/issues
Author-email: Thomas Xin <thomasxin@gmail.com>
License: MIT
License-File: LICENSE
Classifier: Programming Language :: Python :: 3
Requires-Python: >=3.8
Requires-Dist: niquests>=3.15.2
Requires-Dist: urllib3-future>=2.13.908
